{
  "name": "Open in Chrome Browser",
  "description": "Open current page, link, or all tabs in the Chrome browser.",
  "version": "0.3.1.1",
  "manifest_version": 2,
  "permissions": [
    "storage",
    "tabs",
    "contextMenus",
    "nativeMessaging"
  ],
  "optional_permissions": [
    "downloads"
  ],
  "icons": {
    "16": "data/icons/16.png",
    "32": "data/icons/32.png",
    "48": "data/icons/48.png",
    "64": "data/icons/64.png",
    "128": "data/icons/128.png",
    "256": "data/icons/256.png",
    "512": "data/icons/512.png"
  },
  "background": {
    "scripts": [
      "/v2/chrome.contextMenus.create.js",
      "/v2/chrome.runtime.js",
      "/v2/chrome.tabs.query.js",
      "/v2/chrome.action.js",
      "config.js",
      "context.js",
      "worker.js"
    ]
  },
  "storage": {
    "managed_schema": "schema.json"
  },
  "homepage_url": "https://add0n.com/open-in.html?from=chrome",
  "content_scripts": [
    {
      "js": [
        "data/inject.js"
      ],
      "matches": [
        "<all_urls>"
      ],
      "run_at": "document_start",
      "all_frames": true,
      "match_about_blank": true
    }
  ],
  "options_ui": {
    "page": "data/options/index.html",
    "open_in_tab": true
  },
  "commands": {
    "_execute_browser_action": {}
  },
  "browser_action": {},
  "browser_specific_settings": {
    "gecko": {
      "id": "{086f665e-6a55-4107-9147-f9a14e72b137}"
    }
  }
}